yabtool/__init__.py
yabtool/__main__.py
yabtool/gen_password.py
yabtool/gen_uid.py
yabtool/version.py
yabtool/yabtool_application.py
yabtool/yabtool_flow_orchestrator.py
yabtool/yabtool_stat.py
yabtool/config/config.yaml
yabtool/shared/__init__.py
yabtool/shared/base.py
yabtool/shared/jinja2_helpers.py
yabtool/supported_notifications/__init__.py
yabtool/supported_notifications/email_notifications.py
yabtool/supported_steps/__init__.py
yabtool/supported_steps/base.py
yabtool/supported_steps/factory.py
yabtool/supported_steps/s3_steps_shared.py
yabtool/supported_steps/s3boto_client.py
yabtool/supported_steps/shared.py
yabtool/supported_steps/step_calculate_file_hash_and_save_to_file.py
yabtool/supported_steps/step_compress_file_with_7z.py
yabtool/supported_steps/step_make_directory_for_backup.py
yabtool/supported_steps/step_make_firebird_database_backup.py
yabtool/supported_steps/step_make_healthchecks_ping.py
yabtool/supported_steps/step_make_pg_win_database_backup.py
yabtool/supported_steps/step_s3_multipart_upload_with_rotation.py
yabtool/supported_steps/step_s3_strict_uploader.py
yabtool/supported_steps/step_validate_7z_archive.py
yabtool-0.9.0.2.dist-info/LICENSE
yabtool-0.9.0.2.dist-info/METADATA
yabtool-0.9.0.2.dist-info/WHEEL
yabtool-0.9.0.2.dist-info/top_level.txt
yabtool-0.9.0.2.dist-info/RECORD
